README.rst
setup.py
kvcomcon/__init__.py
kvcomcon.egg-info/PKG-INFO
kvcomcon.egg-info/SOURCES.txt
kvcomcon.egg-info/dependency_links.txt
kvcomcon.egg-info/pbr.json
kvcomcon.egg-info/top_level.txt
kvcomcon.egg-info/zip-safe
test/test.py