Metadata-Version: 1.0
Name: kvcomcon
Version: 1.0.0
Summary: key-value-comment config
Home-page: https://github.com/nicholasbishop/kvcomcon
Author: Nicholas Bishop
Author-email: nicholasbishop@gmail.com
License: Apache License 2.0
Platform: UNKNOWN
